apistar_jwt/__init__.py
apistar_jwt/decorators.py
apistar_jwt/exceptions.py
apistar_jwt/token.py
apistar_jwt/utils.py
apistar_jwt-0.5.0.dist-info/METADATA
apistar_jwt-0.5.0.dist-info/RECORD
apistar_jwt-0.5.0.dist-info/WHEEL
apistar_jwt-0.5.0.dist-info/top_level.txt
