Metadata-Version: 2.1
Name: apistar-jwt
Version: 0.5.0
Summary: A JSON Web Token Component for API Star
Home-page: https://github.com/audiolion/apistar-jwt
Author: Ryan Castner
Author-email: castner.rr@gmail.com
License: MIT license
Keywords: apistar_jwt
Platform: UNKNOWN
Classifier: Development Status :: 2 - Pre-Alpha
Classifier: Intended Audience :: Developers
Classifier: License :: OSI Approved :: MIT License
Classifier: Natural Language :: English
Classifier: Programming Language :: Python :: 3
Classifier: Programming Language :: Python :: 3.5
Classifier: Programming Language :: Python :: 3.6
Requires-Dist: apistar (>=0.4)
Requires-Dist: PyJWT
